{
  "placeholderImages": [
    {
      "id": "prod_Bowl-&-Basket_1",
      "productName": "Bowl & Basket Avocado Oil",
      "imageUrl": "https://images.unsplash.com/photo-1605301384598-a3d89b9149ea?q=80&w=600",
      "imageHint": "avocado oil bottle"
    },
    {
      "id": "prod_Bowl-&-Basket_2",
      "productName": "Bowl & Basket Kettle Chips",
      "imageUrl": "https://images.unsplash.com/photo-1588704487282-e7c65b93933e?q=80&w=600",
      "imageHint": "kettle chips bag"
    },
    {
      "id": "prod_Bowl-&-Basket_3",
      "productName": "Bowl & Basket Milk",
      "imageUrl": "https://images.unsplash.com/photo-1635436339396-3e04a4a5879a?q=80&w=600",
      "imageHint": "milk gallon jug"
    },
    {
      "id": "prod_Bowl-&-Basket_4",
      "productName": "Bowl & Basket Spring Water",
      "imageUrl": "https://images.unsplash.com/photo-1543253724-358c9b42937a?q=80&w=600",
      "imageHint": "water bottle pack"
    },
    {
      "id": "prod_Bowl-&-Basket_5",
      "productName": "Bowl & Basket Salad Mix",
      "imageUrl": "https://images.unsplash.com/photo-1550305103-a4e1a062c39d?q=80&w=600",
      "imageHint": "packaged salad bag"
    },
    {
      "id": "prod_Bowl-&-Basket_6",
      "productName": "Bowl & Basket Frozen Vegetables",
      "imageUrl": "https://images.unsplash.com/photo-1583025624738-44d039f9765e?q=80&w=600",
      "imageHint": "frozen vegetable bag"
    },
    {
      "id": "prod_Bowl-&-Basket_7",
      "productName": "Bowl & Basket Low Fat Ice Cream Sandwiches",
      "imageUrl": "https://images.unsplash.com/photo-1625800938639-c02f52c1e48f?q=80&w=600",
      "imageHint": "ice cream sandwich box"
    },
    {
      "id": "prod_Bowl-&-Basket_8",
      "productName": "Bowl & Basket Organic Chipotle Veggie Burgers",
      "imageUrl": "https://images.unsplash.com/photo-1619899383833-911c015957e7?q=80&w=600",
      "imageHint": "veggie burger box"
    },
    {
      "id": "prod_Bowl-&-Basket_9",
      "productName": "Bowl & Basket Korean Inspired Cauliflower Bowl",
      "imageUrl": "https://images.unsplash.com/photo-1630384313348-1335b8857504?q=80&w=600",
      "imageHint": "frozen meal bowl"
    },
    {
      "id": "prod_Bowl-&-Basket_10",
      "productName": "Bowl & Basket Vegan Plant-Based Meatless Cheesesteak Dumplings",
      "imageUrl": "https://images.unsplash.com/photo-1628864703554-bab4d88258a1?q=80&w=600",
      "imageHint": "frozen dumplings bag"
    },
    {
      "id": "prod_Bowl-&-Basket_11",
      "productName": "Bowl & Basket Bath Tissue",
      "imageUrl": "https://images.unsplash.com/photo-1604323832139-3c1a29a39985?q=80&w=600",
      "imageHint": "toilet paper pack"
    },
    {
      "id": "prod_Bowl-&-Basket_12",
      "productName": "Bowl & Basket Paper Towels",
      "imageUrl": "https://images.unsplash.com/photo-1609135394994-3a5c4343a496?q=80&w=600",
      "imageHint": "paper towel rolls"
    },
    {
      "id": "prod_Bowl-&-Basket_13",
      "productName": "Bowl & Basket Deli Roast Beef",
      "imageUrl": "https://images.unsplash.com/photo-1591054198115-f6a6174a77a9?q=80&w=600",
      "imageHint": "packaged deli meat"
    },
    {
      "id": "prod_Bowl-&-Basket_14",
      "productName": "Bowl & Basket Deli Swiss Cheese",
      "imageUrl": "https://images.unsplash.com/photo-1564835415911-35243338bbea?q=80&w=600",
      "imageHint": "packaged sliced cheese"
    },
    {
      "id": "prod_Bowl-&-Basket_15",
      "productName": "Bowl & Basket Fresh Chicken Breast",
      "imageUrl": "https://images.unsplash.com/photo-1613564797125-afe133d74868?q=80&w=600",
      "imageHint": "packaged chicken breast"
    },
    {
      "id": "prod_Bowl-&-Basket_16",
      "productName": "Bowl & Basket Whole Wheat Bread",
      "imageUrl": "https://images.unsplash.com/photo-1598373182133-52452f741796?q=80&w=600",
      "imageHint": "bread loaf"
    },
    {
      "id": "prod_Bowl-&-Basket_17",
      "productName": "Bowl & Basket Organic Eggs",
      "imageUrl": "https://images.unsplash.com/photo-1587573089734-09cb69c0f2b4?q=80&w=600",
      "imageHint": "egg carton"
    },
    {
      "id": "prod_Bowl-&-Basket_18",
      "productName": "Bowl & Basket Shredded Cheddar Cheese",
      "imageUrl": "https://images.unsplash.com/photo-1644783344605-3b7a5a542618?q=80&w=600",
      "imageHint": "shredded cheese bag"
    },
    {
      "id": "prod_Bowl-&-Basket_19",
      "productName": "Bowl & Basket Tomato Ketchup",
      "imageUrl": "https://images.unsplash.com/photo-1585437895315-7a8f9598fd72?q=80&w=600",
      "imageHint": "ketchup bottle"
    },
    {
      "id": "prod_Bowl-&-Basket_20",
      "productName": "Bowl & Basket Olive Oil",
      "imageUrl": "https://images.unsplash.com/photo-1579222384078-622839387258?q=80&w=600",
      "imageHint": "olive oil bottle"
    },
    {
      "id": "prod_Bowl-&-Basket_21",
      "productName": "Bowl & Basket Chocolate Bar",
      "imageUrl": "https://images.unsplash.com/photo-1627462249557-4139f4853b06?q=80&w=600",
      "imageHint": "chocolate bar wrapper"
    },
    {
      "id": "prod_Bowl-&-Basket_22",
      "productName": "Bowl & Basket Almond Butter",
      "imageUrl": "https://images.unsplash.com/photo-1620921280922-12f9937e956b?q=80&w=600",
      "imageHint": "almond butter jar"
    },
    {
      "id": "prod_Bowl-&-Basket_23",
      "productName": "Bowl & Basket Cereal",
      "imageUrl": "https://images.unsplash.com/photo-1585473482704-5d4653634863?q=80&w=600",
      "imageHint": "cereal box"
    },
    {
      "id": "prod_Bowl-&-Basket_24",
      "productName": "Bowl & Basket Granola Bars",
      "imageUrl": "https://images.unsplash.com/photo-1554522965-084a33191334?q=80&w=600",
      "imageHint": "granola bar box"
    },
    {
      "id": "prod_Bowl-&-Basket_25",
      "productName": "Bowl & Basket Greek Yogurt",
      "imageUrl": "https://images.unsplash.com/photo-1559598467-f8b76c8155d0?q=80&w=600",
      "imageHint": "yogurt container"
    },
    {
      "id": "prod_Bowl-&-Basket_26",
      "productName": "Bowl & Basket Coffee Beans",
      "imageUrl": "https://images.unsplash.com/photo-1511537190424-bbbab87ac5eb?q=80&w=600",
      "imageHint": "coffee bean bag"
    },
    {
      "id": "prod_Bowl-&-Basket_27",
      "productName": "Bowl & Basket Butter",
      "imageUrl": "https://images.unsplash.com/photo-1622240506294-0a93a8a3d248?q=80&w=600",
      "imageHint": "butter sticks"
    },
    {
      "id": "prod_Bowl-&-Basket_28",
      "productName": "Bowl & Basket Frozen Pizza",
      "imageUrl": "https://images.unsplash.com/photo-1565299624946-b28f40a0ae38?q=80&w=600",
      "imageHint": "frozen pizza box"
    },
    {
      "id": "prod_Wholesome-Pantry_29",
      "productName": "Wholesome Pantry Avocado Oil",
      "imageUrl": "https://images.unsplash.com/photo-1605301384598-a3d89b9149ea?q=80&w=600",
      "imageHint": "avocado oil bottle"
    },
    {
      "id": "prod_Wholesome-Pantry_30",
      "productName": "Wholesome Pantry Kettle Chips",
      "imageUrl": "https://images.unsplash.com/photo-1588704487282-e7c65b93933e?q=80&w=600",
      "imageHint": "chip bag"
    },
    {
      "id": "prod_Wholesome-Pantry_31",
      "productName": "Wholesome Pantry Milk",
      "imageUrl": "https://images.unsplash.com/photo-1635436339396-3e04a4a5879a?q=80&w=600",
      "imageHint": "milk gallon jug"
    },
    {
      "id": "prod_Wholesome-Pantry_32",
      "productName": "Wholesome Pantry Spring Water",
      "imageUrl": "https://images.unsplash.com/photo-1543253724-358c9b42937a?q=80&w=600",
      "imageHint": "water bottle pack"
    },
    {
      "id": "prod_Wholesome-Pantry_33",
      "productName": "Wholesome Pantry Salad Mix",
      "imageUrl": "https://images.unsplash.com/photo-1550305103-a4e1a062c39d?q=80&w=600",
      "imageHint": "packaged salad bag"
    },
    {
      "id": "prod_Wholesome-Pantry_34",
      "productName": "Wholesome Pantry Frozen Vegetables",
      "imageUrl": "https://images.unsplash.com/photo-1583025624738-44d039f9765e?q=80&w=600",
      "imageHint": "frozen peas bag"
    },
    {
      "id": "prod_Wholesome-Pantry_35",
      "productName": "Wholesome Pantry Low Fat Ice Cream Sandwiches",
      "imageUrl": "https://images.unsplash.com/photo-1625800938639-c02f52c1e48f?q=80&w=600",
      "imageHint": "ice cream sandwich box"
    },
    {
      "id": "prod_Wholesome-Pantry_36",
      "productName": "Wholesome Pantry Organic Chipotle Veggie Burgers",
      "imageUrl": "https://images.unsplash.com/photo-1619899383833-911c015957e7?q=80&w=600",
      "imageHint": "veggie burger box"
    },
    {
      "id": "prod_Wholesome-Pantry_37",
      "productName": "Wholesome Pantry Korean Inspired Cauliflower Bowl",
      "imageUrl": "https://images.unsplash.com/photo-1630384313348-1335b8857504?q=80&w=600",
      "imageHint": "frozen meal bowl"
    },
    {
      "id": "prod_Wholesome-Pantry_38",
      "productName": "Wholesome Pantry Vegan Plant-Based Meatless Cheesesteak Dumplings",
      "imageUrl": "https://images.unsplash.com/photo-1628864703554-bab4d88258a1?q=80&w=600",
      "imageHint": "frozen dumplings bag"
    },
    {
      "id": "prod_Wholesome-Pantry_39",
      "productName": "Wholesome Pantry Bath Tissue",
      "imageUrl": "https://images.unsplash.com/photo-1604323832139-3c1a29a39985?q=80&w=600",
      "imageHint": "toilet paper pack"
    },
    {
      "id": "prod_Wholesome-Pantry_40",
      "productName": "Wholesome Pantry Paper Towels",
      "imageUrl": "https://images.unsplash.com/photo-1609135394994-3a5c4343a496?q=80&w=600",
      "imageHint": "paper towel rolls"
    },
    {
      "id": "prod_Wholesome-Pantry_41",
      "productName": "Wholesome Pantry Deli Roast Beef",
      "imageUrl": "https://images.unsplash.com/photo-1591054198115-f6a6174a77a9?q=80&w=600",
      "imageHint": "packaged deli meat"
    },
    {
      "id": "prod_Wholesome-Pantry_42",
      "productName": "Wholesome Pantry Deli Swiss Cheese",
      "imageUrl": "https://images.unsplash.com/photo-1564835415911-35243338bbea?q=80&w=600",
      "imageHint": "packaged sliced cheese"
    },
    {
      "id": "prod_Wholesome-Pantry_43",
      "productName": "Wholesome Pantry Fresh Chicken Breast",
      "imageUrl": "https://images.unsplash.com/photo-1613564797125-afe133d74868?q=80&w=600",
      "imageHint": "packaged chicken breast"
    },
    {
      "id": "prod_Wholesome-Pantry_44",
      "productName": "Wholesome Pantry Whole Wheat Bread",
      "imageUrl": "https://images.unsplash.com/photo-1598373182133-52452f741796?q=80&w=600",
      "imageHint": "bread loaf"
    },
    {
      "id": "prod_Wholesome-Pantry_45",
      "productName": "Wholesome Pantry Organic Eggs",
      "imageUrl": "https://images.unsplash.com/photo-1587573089734-09cb69c0f2b4?q=80&w=600",
      "imageHint": "egg carton"
    },
    {
      "id": "prod_Wholesome-Pantry_46",
      "productName": "Wholesome Pantry Shredded Cheddar Cheese",
      "imageUrl": "https://images.unsplash.com/photo-1644783344605-3b7a5a542618?q=80&w=600",
      "imageHint": "shredded cheese bag"
    },
    {
      "id": "prod_Wholesome-Pantry_47",
      "productName": "Wholesome Pantry Tomato Ketchup",
      "imageUrl": "https://images.unsplash.com/photo-1585437895315-7a8f9598fd72?q=80&w=600",
      "imageHint": "ketchup bottle"
    },
    {
      "id": "prod_Wholesome-Pantry_48",
      "productName": "Wholesome Pantry Olive Oil",
      "imageUrl": "https://images.unsplash.com/photo-1579222384078-622839387258?q=80&w=600",
      "imageHint": "olive oil bottle"
    },
    {
      "id": "prod_Wholesome-Pantry_49",
      "productName": "Wholesome Pantry Chocolate Bar",
      "imageUrl": "https://images.unsplash.com/photo-1627462249557-4139f4853b06?q=80&w=600",
      "imageHint": "chocolate bar wrapper"
    },
    {
      "id": "prod_Wholesome-Pantry_50",
      "productName": "Wholesome Pantry Almond Butter",
      "imageUrl": "https://images.unsplash.com/photo-1620921280922-12f9937e956b?q=80&w=600",
      "imageHint": "almond butter jar"
    },
    {
      "id": "prod_Wholesome-Pantry_51",
      "productName": "Wholesome Pantry Cereal",
      "imageUrl": "https://images.unsplash.com/photo-1585473482704-5d4653634863?q=80&w=600",
      "imageHint": "cereal box"
    },
    {
      "id": "prod_Wholesome-Pantry_52",
      "productName": "Wholesome Pantry Granola Bars",
      "imageUrl": "https://images.unsplash.com/photo-1554522965-084a33191334?q=80&w=600",
      "imageHint": "granola bar box"
    },
    {
      "id": "prod_Wholesome-Pantry_53",
      "productName": "Wholesome Pantry Greek Yogurt",
      "imageUrl": "https://images.unsplash.com/photo-1559598467-f8b76c8155d0?q=80&w=600",
      "imageHint": "yogurt container"
    },
    {
      "id": "prod_Wholesome-Pantry_54",
      "productName": "Wholesome Pantry Coffee Beans",
      "imageUrl": "https://images.unsplash.com/photo-1511537190424-bbbab87ac5eb?q=80&w=600",
      "imageHint": "coffee bean bag"
    },
    {
      "id": "prod_Wholesome-Pantry_55",
      "productName": "Wholesome Pantry Butter",
      "imageUrl": "https://images.unsplash.com/photo-1622240506294-0a93a8a3d248?q=80&w=600",
      "imageHint": "butter sticks"
    },
    {
      "id": "prod_Wholesome-Pantry_56",
      "productName": "Wholesome Pantry Frozen Pizza",
      "imageUrl": "https://images.unsplash.com/photo-1565299624946-b28f40a0ae38?q=80&w=600",
      "imageHint": "frozen pizza box"
    },
    {
      "id": "prod_Paperbird_57",
      "productName": "Paperbird Avocado Oil",
      "imageUrl": "https://images.unsplash.com/photo-1605301384598-a3d89b9149ea?q=80&w=600",
      "imageHint": "avocado oil bottle"
    },
    {
      "id": "prod_Paperbird_58",
      "productName": "Paperbird Kettle Chips",
      "imageUrl": "https://images.unsplash.com/photo-1588704487282-e7c65b93933e?q=80&w=600",
      "imageHint": "kettle chips bag"
    },
    {
      "id": "prod_Paperbird_59",
      "productName": "Paperbird Milk",
      "imageUrl": "https://images.unsplash.com/photo-1635436339396-3e04a4a5879a?q=80&w=600",
      "imageHint": "milk gallon jug"
    },
    {
      "id": "prod_Paperbird_60",
      "productName": "Paperbird Spring Water",
      "imageUrl": "https://images.unsplash.com/photo-1543253724-358c9b42937a?q=80&w=600",
      "imageHint": "water bottle pack"
    },
    {
      "id": "prod_Paperbird_61",
      "productName": "Paperbird Salad Mix",
      "imageUrl": "https://images.unsplash.com/photo-1550305103-a4e1a062c39d?q=80&w=600",
      "imageHint": "packaged salad bag"
    },
    {
      "id": "prod_Paperbird_62",
      "productName": "Paperbird Frozen Vegetables",
      "imageUrl": "https://images.unsplash.com/photo-1583025624738-44d039f9765e?q=80&w=600",
      "imageHint": "frozen vegetable bag"
    },
    {
      "id": "prod_Paperbird_63",
      "productName": "Paperbird Low Fat Ice Cream Sandwiches",
      "imageUrl": "https://images.unsplash.com/photo-1625800938639-c02f52c1e48f?q=80&w=600",
      "imageHint": "ice cream sandwich box"
    },
    {
      "id": "prod_Paperbird_64",
      "productName": "Paperbird Organic Chipotle Veggie Burgers",
      "imageUrl": "https://images.unsplash.com/photo-1619899383833-911c015957e7?q=80&w=600",
      "imageHint": "veggie burger box"
    },
    {
      "id": "prod_Paperbird_65",
      "productName": "Paperbird Korean Inspired Cauliflower Bowl",
      "imageUrl": "https://images.unsplash.com/photo-1630384313348-1335b8857504?q=80&w=600",
      "imageHint": "frozen meal bowl"
    },
    {
      "id": "prod_Paperbird_66",
      "productName": "Paperbird Vegan Plant-Based Meatless Cheesesteak Dumplings",
      "imageUrl": "https://images.unsplash.com/photo-1628864703554-bab4d88258a1?q=80&w=600",
      "imageHint": "frozen dumplings bag"
    },
    {
      "id": "prod_Paperbird_67",
      "productName": "Paperbird Bath Tissue",
      "imageUrl": "https://images.unsplash.com/photo-1604323832139-3c1a29a39985?q=80&w=600",
      "imageHint": "toilet paper pack"
    },
    {
      "id": "prod_Paperbird_68",
      "productName": "Paperbird Paper Towels",
      "imageUrl": "https://images.unsplash.com/photo-1609135394994-3a5c4343a496?q=80&w=600",
      "imageHint": "paper towel rolls"
    },
    {
      "id": "prod_Paperbird_69",
      "productName": "Paperbird Deli Roast Beef",
      "imageUrl": "https://images.unsplash.com/photo-1591054198115-f6a6174a77a9?q=80&w=600",
      "imageHint": "packaged deli meat"
    },
    {
      "id": "prod_Paperbird_70",
      "productName": "Paperbird Deli Swiss Cheese",
      "imageUrl": "https://images.unsplash.com/photo-1564835415911-35243338bbea?q=80&w=600",
      "imageHint": "packaged sliced cheese"
    },
    {
      "id": "prod_Paperbird_71",
      "productName": "Paperbird Fresh Chicken Breast",
      "imageUrl": "https://images.unsplash.com/photo-1613564797125-afe133d74868?q=80&w=600",
      "imageHint": "packaged chicken breast"
    },
    {
      "id": "prod_Paperbird_72",
      "productName": "Paperbird Whole Wheat Bread",
      "imageUrl": "https://images.unsplash.com/photo-1598373182133-52452f741796?q=80&w=600",
      "imageHint": "bread loaf"
    },
    {
      "id": "prod_Paperbird_73",
      "productName": "Paperbird Organic Eggs",
      "imageUrl": "https://images.unsplash.com/photo-1587573089734-09cb69c0f2b4?q=80&w=600",
      "imageHint": "egg carton"
    },
    {
      "id": "prod_Paperbird_74",
      "productName": "Paperbird Shredded Cheddar Cheese",
      "imageUrl": "https://images.unsplash.com/photo-1644783344605-3b7a5a542618?q=80&w=600",
      "imageHint": "shredded cheese bag"
    },
    {
      "id": "prod_Paperbird_75",
      "productName": "Paperbird Tomato Ketchup",
      "imageUrl": "https://images.unsplash.com/photo-1585437895315-7a8f9598fd72?q=80&w=600",
      "imageHint": "ketchup bottle"
    },
    {
      "id": "prod_Paperbird_76",
      "productName": "Paperbird Olive Oil",
      "imageUrl": "https://images.unsplash.com/photo-1579222384078-622839387258?q=80&w=600",
      "imageHint": "olive oil bottle"
    },
    {
      "id": "prod_Paperbird_77",
      "productName": "Paperbird Chocolate Bar",
      "imageUrl": "https://images.unsplash.com/photo-1627462249557-4139f4853b06?q=80&w=600",
      "imageHint": "chocolate bar wrapper"
    },
    {
      "id": "prod_Paperbird_78",
      "productName": "Paperbird Almond Butter",
      "imageUrl": "https://images.unsplash.com/photo-1620921280922-12f9937e956b?q=80&w=600",
      "imageHint": "almond butter jar"
    },
    {
      "id": "prod_Paperbird_79",
      "productName": "Paperbird Cereal",
      "imageUrl": "https://images.unsplash.com/photo-1585473482704-5d4653634863?q=80&w=600",
      "imageHint": "cereal box"
    },
    {
      "id": "prod_Paperbird_80",
      "productName": "Paperbird Granola Bars",
      "imageUrl": "https://images.unsplash.com/photo-1554522965-084a33191334?q=80&w=600",
      "imageHint": "granola bar box"
    },
    {
      "id": "prod_Paperbird_81",
      "productName": "Paperbird Greek Yogurt",
      "imageUrl": "https://images.unsplash.com/photo-1559598467-f8b76c8155d0?q=80&w=600",
      "imageHint": "yogurt container"
    },
    {
      "id": "prod_Paperbird_82",
      "productName": "Paperbird Coffee Beans",
      "imageUrl": "https://images.unsplash.com/photo-1511537190424-bbbab87ac5eb?q=80&w=600",
      "imageHint": "coffee bean bag"
    },
    {
      "id": "prod_Paperbird_83",
      "productName": "Paperbird Butter",
      "imageUrl": "https://images.unsplash.com/photo-1622240506294-0a93a8a3d248?q=80&w=600",
      "imageHint": "butter sticks"
    },
    {
      "id": "prod_Paperbird_84",
      "productName": "Paperbird Frozen Pizza",
      "imageUrl": "https://images.unsplash.com/photo-1565299624946-b28f40a0ae38?q=80&w=600",
      "imageHint": "frozen pizza box"
    },
    {
      "id": "prod_Black-Bear-of-the-Black-Forest_85",
      "productName": "Black Bear of the Black Forest Avocado Oil",
      "imageUrl": "https://images.unsplash.com/photo-1605301384598-a3d89b9149ea?q=80&w=600",
      "imageHint": "avocado oil bottle"
    },
    {
      "id": "prod_Black-Bear-of-the-Black-Forest_86",
      "productName": "Black Bear of the Black Forest Kettle Chips",
      "imageUrl": "https://images.unsplash.com/photo-1588704487282-e7c65b93933e?q=80&w=600",
      "imageHint": "kettle chips bag"
    },
    {
      "id": "prod_Black-Bear-of-the-Black-Forest_87",
      "productName": "Black Bear of the Black Forest Milk",
      "imageUrl": "https://images.unsplash.com/photo-1635436339396-3e04a4a5879a?q=80&w=600",
      "imageHint": "milk gallon jug"
    },
    {
      "id": "prod_Black-Bear-of-the-Black-Forest_88",
      "productName": "Black Bear of the Black Forest Spring Water",
      "imageUrl": "https://images.unsplash.com/photo-1543253724-358c9b42937a?q=80&w=600",
      "imageHint": "water bottle pack"
    },
    {
      "id": "prod_Black-Bear-of-the-Black-Forest_89",
      "productName": "Black Bear of the Black Forest Salad Mix",
      "imageUrl": "https://images.unsplash.com/photo-1550305103-a4e1a062c39d?q=80&w=600",
      "imageHint": "packaged salad bag"
    },
    {
      "id": "prod_Black-Bear-of-the-Black-Forest_90",
      "productName": "Black Bear of the Black Forest Frozen Vegetables",
      "imageUrl": "https://images.unsplash.com/photo-1583025624738-44d039f9765e?q=80&w=600",
      "imageHint": "frozen vegetable bag"
    },
    {
      "id": "prod_Black-Bear-of-the-Black-Forest_91",
      "productName": "Black Bear of the Black Forest Low Fat Ice Cream Sandwiches",
      "imageUrl": "https://images.unsplash.com/photo-1625800938639-c02f52c1e48f?q=80&w=600",
      "imageHint": "ice cream sandwich box"
    },
    {
      "id": "prod_Black-Bear-of-the-Black-Forest_92",
      "productName": "Black Bear of the Black Forest Organic Chipotle Veggie Burgers",
      "imageUrl": "https://images.unsplash.com/photo-1619899383833-911c015957e7?q=80&w=600",
      "imageHint": "veggie burger box"
    },
    {
      "id": "prod_Black-Bear-of-the-Black-Forest_93",
      "productName": "Black Bear of the Black Forest Korean Inspired Cauliflower Bowl",
      "imageUrl": "https://images.unsplash.com/photo-1630384313348-1335b8857504?q=80&w=600",
      "imageHint": "frozen meal bowl"
    },
    {
      "id": "prod_Black-Bear-of-the-Black-Forest_94",
      "productName": "Black Bear of the Black Forest Vegan Plant-Based Meatless Cheesesteak Dumplings",
      "imageUrl": "https://images.unsplash.com/photo-1628864703554-bab4d88258a1?q=80&w=600",
      "imageHint": "frozen dumplings bag"
    },
    {
      "id": "prod_Black-Bear-of-the-Black-Forest_95",
      "productName": "Black Bear of the Black Forest Bath Tissue",
      "imageUrl": "https://images.unsplash.com/photo-1604323832139-3c1a29a39985?q=80&w=600",
      "imageHint": "toilet paper pack"
    },
    {
      "id": "prod_Black-Bear-of-the-Black-Forest_96",
      "productName": "Black Bear of the Black Forest Paper Towels",
      "imageUrl": "https://images.unsplash.com/photo-1609135394994-3a5c4343a496?q=80&w=600",
      "imageHint": "paper towel rolls"
    },
    {
      "id": "prod_Black-Bear-of-the-Black-Forest_97",
      "productName": "Black Bear of the Black Forest Deli Roast Beef",
      "imageUrl": "https://images.unsplash.com/photo-1591054198115-f6a6174a77a9?q=80&w=600",
      "imageHint": "packaged deli meat"
    },
    {
      "id": "prod_Black-Bear-of-the-Black-Forest_98",
      "productName": "Black Bear of the Black Forest Deli Swiss Cheese",
      "imageUrl": "https://images.unsplash.com/photo-1564835415911-35243338bbea?q=80&w=600",
      "imageHint": "packaged sliced cheese"
    },
    {
      "id": "prod_Black-Bear-of-the-Black-Forest_99",
      "productName": "Black Bear of the Black Forest Fresh Chicken Breast",
      "imageUrl": "https://images.unsplash.com/photo-1613564797125-afe133d74868?q=80&w=600",
      "imageHint": "packaged chicken breast"
    },
    {
      "id": "prod_Black-Bear-of-the-Black-Forest_100",
      "productName": "Black Bear of the Black Forest Whole Wheat Bread",
      "imageUrl": "https://images.unsplash.com/photo-1598373182133-52452f741796?q=80&w=600",
      "imageHint": "bread loaf"
    },
    {
      "id": "prod_Black-Bear-of-the-Black-Forest_101",
      "productName": "Black Bear of the Black Forest Organic Eggs",
      "imageUrl": "https://images.unsplash.com/photo-1587573089734-09cb69c0f2b4?q=80&w=600",
      "imageHint": "egg carton"
    },
    {
      "id": "prod_Black-Bear-of-the-Black-Forest_102",
      "productName": "Black Bear of the Black Forest Shredded Cheddar Cheese",
      "imageUrl": "https://images.unsplash.com/photo-1644783344605-3b7a5a542618?q=80&w=600",
      "imageHint": "shredded cheese bag"
    },
    {
      "id": "prod_Black-Bear-of-the-Black-Forest_103",
      "productName": "Black Bear of the Black Forest Tomato Ketchup",
      "imageUrl": "https://images.unsplash.com/photo-1585437895315-7a8f9598fd72?q=80&w=600",
      "imageHint": "ketchup bottle"
    },
    {
      "id": "prod_Black-Bear-of-the-Black-Forest_104",
      "productName": "Black Bear of the Black Forest Olive Oil",
      "imageUrl": "https://images.unsplash.com/photo-1579222384078-622839387258?q=80&w=600",
      "imageHint": "olive oil bottle"
    },
    {
      "id": "prod_Black-Bear-of-the-Black-Forest_105",
      "productName": "Black Bear of the Black Forest Chocolate Bar",
      "imageUrl": "https://images.unsplash.com/photo-1627462249557-4139f4853b06?q=80&w=600",
      "imageHint": "chocolate bar wrapper"
    },
    {
      "id": "prod_Black-Bear-of-the-Black-Forest_106",
      "productName": "Black Bear of the Black Forest Almond Butter",
      "imageUrl": "https://images.unsplash.com/photo-1620921280922-12f9937e956b?q=80&w=600",
      "imageHint": "almond butter jar"
    },
    {
      "id": "prod_Black-Bear-of-the-Black-Forest_107",
      "productName": "Black Bear of the Black Forest Cereal",
      "imageUrl": "https://images.unsplash.com/photo-1585473482704-5d4653634863?q=80&w=600",
      "imageHint": "cereal box"
    },
    {
      "id": "prod_Black-Bear-of-the-Black-Forest_108",
      "productName": "Black Bear of the Black Forest Granola Bars",
      "imageUrl": "https://images.unsplash.com/photo-1554522965-084a33191334?q=80&w=600",
      "imageHint": "granola bar box"
    },
    {
      "id": "prod_Black-Bear-of-the-Black-Forest_109",
      "productName": "Black Bear of the Black Forest Greek Yogurt",
      "imageUrl": "https://images.unsplash.com/photo-1559598467-f8b76c8155d0?q=80&w=600",
      "imageHint": "yogurt container"
    },
    {
      "id": "prod_Black-Bear-of-the-Black-Forest_110",
      "productName": "Black Bear of the Black Forest Coffee Beans",
      "imageUrl": "https://images.unsplash.com/photo-1511537190424-bbbab87ac5eb?q=80&w=600",
      "imageHint": "coffee bean bag"
    },
    {
      "id": "prod_Black-Bear-of-the-Black-Forest_111",
      "productName": "Black Bear of the Black Forest Butter",
      "imageUrl": "https://images.unsplash.com/photo-1622240506294-0a93a8a3d248?q=80&w=600",
      "imageHint": "butter sticks"
    },
    {
      "id": "prod_Black-Bear-of-the-Black-Forest_112",
      "productName": "Black Bear of the Black Forest Frozen Pizza",
      "imageUrl": "https://images.unsplash.com/photo-1565299624946-b28f40a0ae38?q=80&w=600",
      "imageHint": "frozen pizza box"
    },
    {
      "id": "prod_ShopRite-Kitchen_113",
      "productName": "ShopRite Kitchen Avocado Oil",
      "imageUrl": "https://images.unsplash.com/photo-1605301384598-a3d89b9149ea?q=80&w=600",
      "imageHint": "avocado oil bottle"
    },
    {
      "id": "prod_ShopRite-Kitchen_114",
      "productName": "ShopRite Kitchen Kettle Chips",
      "imageUrl": "https://images.unsplash.com/photo-1588704487282-e7c65b93933e?q=80&w=600",
      "imageHint": "kettle chips bag"
    },
    {
      "id": "prod_ShopRite-Kitchen_115",
      "productName": "ShopRite Kitchen Milk",
      "imageUrl": "https://images.unsplash.com/photo-1635436339396-3e04a4a5879a?q=80&w=600",
      "imageHint": "milk gallon jug"
    },
    {
      "id": "prod_ShopRite-Kitchen_116",
      "productName": "ShopRite Kitchen Spring Water",
      "imageUrl": "https://images.unsplash.com/photo-1543253724-358c9b42937a?q=80&w=600",
      "imageHint": "water bottle pack"
    },
    {
      "id": "prod_ShopRite-Kitchen_117",
      "productName": "ShopRite Kitchen Salad Mix",
      "imageUrl": "https://images.unsplash.com/photo-1550305103-a4e1a062c39d?q=80&w=600",
      "imageHint": "packaged salad bag"
    },
    {
      "id": "prod_ShopRite-Kitchen_118",
      "productName": "ShopRite Kitchen Frozen Vegetables",
      "imageUrl": "https://images.unsplash.com/photo-1583025624738-44d039f9765e?q=80&w=600",
      "imageHint": "frozen vegetable bag"
    },
    {
      "id": "prod_ShopRite-Kitchen_119",
      "productName": "ShopRite Kitchen Low Fat Ice Cream Sandwiches",
      "imageUrl": "https://images.unsplash.com/photo-1625800938639-c02f52c1e48f?q=80&w=600",
      "imageHint": "ice cream sandwich box"
    },
    {
      "id": "prod_ShopRite-Kitchen_120",
      "productName": "ShopRite Kitchen Organic Chipotle Veggie Burgers",
      "imageUrl": "https://images.unsplash.com/photo-1619899383833-911c015957e7?q=80&w=600",
      "imageHint": "veggie burger box"
    },
    {
      "id": "prod_ShopRite-Kitchen_121",
      "productName": "ShopRite Kitchen Korean Inspired Cauliflower Bowl",
      "imageUrl": "https://images.unsplash.com/photo-1630384313348-1335b8857504?q=80&w=600",
      "imageHint": "frozen meal bowl"
    },
    {
      "id": "prod_ShopRite-Kitchen_122",
      "productName": "ShopRite Kitchen Vegan Plant-Based Meatless Cheesesteak Dumplings",
      "imageUrl": "https://images.unsplash.com/photo-1628864703554-bab4d88258a1?q=80&w=600",
      "imageHint": "frozen dumplings bag"
    },
    {
      "id": "prod_ShopRite-Kitchen_123",
      "productName": "ShopRite Kitchen Bath Tissue",
      "imageUrl": "https://images.unsplash.com/photo-1604323832139-3c1a29a39985?q=80&w=600",
      "imageHint": "toilet paper pack"
    },
    {
      "id": "prod_ShopRite-Kitchen_124",
      "productName": "ShopRite Kitchen Paper Towels",
      "imageUrl": "https://images.unsplash.com/photo-1609135394994-3a5c4343a496?q=80&w=600",
      "imageHint": "paper towel rolls"
    },
    {
      "id": "prod_ShopRite-Kitchen_125",
      "productName": "ShopRite Kitchen Deli Roast Beef",
      "imageUrl": "https://images.unsplash.com/photo-1591054198115-f6a6174a77a9?q=80&w=600",
      "imageHint": "packaged deli meat"
    },
    {
      "id": "prod_ShopRite-Kitchen_126",
      "productName": "ShopRite Kitchen Deli Swiss Cheese",
      "imageUrl": "https://images.unsplash.com/photo-1564835415911-35243338bbea?q=80&w=600",
      "imageHint": "packaged sliced cheese"
    },
    {
      "id": "prod_ShopRite-Kitchen_127",
      "productName": "ShopRite Kitchen Fresh Chicken Breast",
      "imageUrl": "https://images.unsplash.com/photo-1613564797125-afe133d74868?q=80&w=600",
      "imageHint": "packaged chicken breast"
    },
    {
      "id": "prod_ShopRite-Kitchen_128",
      "productName": "ShopRite Kitchen Whole Wheat Bread",
      "imageUrl": "https://images.unsplash.com/photo-1598373182133-52452f741796?q=80&w=600",
      "imageHint": "bread loaf"
    },
    {
      "id": "prod_ShopRite-Kitchen_129",
      "productName": "ShopRite Kitchen Organic Eggs",
      "imageUrl": "https://images.unsplash.com/photo-1587573089734-09cb69c0f2b4?q=80&w=600",
      "imageHint": "egg carton"
    },
    {
      "id": "prod_ShopRite-Kitchen_130",
      "productName": "ShopRite Kitchen Shredded Cheddar Cheese",
      "imageUrl": "https://images.unsplash.com/photo-1644783344605-3b7a5a542618?q=80&w=600",
      "imageHint": "shredded cheese bag"
    },
    {
      "id": "prod_ShopRite-Kitchen_131",
      "productName": "ShopRite Kitchen Tomato Ketchup",
      "imageUrl": "https://images.unsplash.com/photo-1585437895315-7a8f9598fd72?q=80&w=600",
      "imageHint": "ketchup bottle"
    },
    {
      "id": "prod_ShopRite-Kitchen_132",
      "productName": "ShopRite Kitchen Olive Oil",
      "imageUrl": "https://images.unsplash.com/photo-1579222384078-622839387258?q=80&w=600",
      "imageHint": "olive oil bottle"
    },
    {
      "id": "prod_ShopRite-Kitchen_133",
      "productName": "ShopRite Kitchen Chocolate Bar",
      "imageUrl": "https://images.unsplash.com/photo-1627462249557-4139f4853b06?q=80&w=600",
      "imageHint": "chocolate bar wrapper"
    },
    {
      "id": "prod_ShopRite-Kitchen_134",
      "productName": "ShopRite Kitchen Almond Butter",
      "imageUrl": "https://images.unsplash.com/photo-1620921280922-12f9937e956b?q=80&w=600",
      "imageHint": "almond butter jar"
    },
    {
      "id": "prod_ShopRite-Kitchen_135",
      "productName": "ShopRite Kitchen Cereal",
      "imageUrl": "https://images.unsplash.com/photo-1585473482704-5d4653634863?q=80&w=600",
      "imageHint": "cereal box"
    },
    {
      "id": "prod_ShopRite-Kitchen_136",
      "productName": "ShopRite Kitchen Granola Bars",
      "imageUrl": "https://images.unsplash.com/photo-1554522965-084a33191334?q=80&w=600",
      "imageHint": "granola bar box"
    },
    {
      "id": "prod_ShopRite-Kitchen_137",
      "productName": "ShopRite Kitchen Greek Yogurt",
      "imageUrl": "https://images.unsplash.com/photo-1559598467-f8b76c8155d0?q=80&w=600",
      "imageHint": "yogurt container"
    },
    {
      "id": "prod_ShopRite-Kitchen_138",
      "productName": "ShopRite Kitchen Coffee Beans",
      "imageUrl": "https://images.unsplash.com/photo-1511537190424-bbbab87ac5eb?q=80&w=600",
      "imageHint": "coffee bean bag"
    },
    {
      "id": "prod_ShopRite-Kitchen_139",
      "productName": "ShopRite Kitchen Butter",
      "imageUrl": "https://images.unsplash.com/photo-1622240506294-0a93a8a3d248?q=80&w=600",
      "imageHint": "butter sticks"
    },
    {
      "id": "prod_ShopRite-Kitchen_140",
      "productName": "ShopRite Kitchen Frozen Pizza",
      "imageUrl": "https://images.unsplash.com/photo-1565299624946-b28f40a0ae38?q=80&w=600",
      "imageHint": "frozen pizza box"
    },
    {
      "id": "prod_Cape-Gourmet_141",
      "productName": "Cape Gourmet Avocado Oil",
      "imageUrl": "https://images.unsplash.com/photo-1605301384598-a3d89b9149ea?q=80&w=600",
      "imageHint": "avocado oil bottle"
    },
    {
      "id": "prod_Cape-Gourmet_142",
      "productName": "Cape Gourmet Kettle Chips",
      "imageUrl": "https://images.unsplash.com/photo-1588704487282-e7c65b93933e?q=80&w=600",
      "imageHint": "kettle chips bag"
    },
    {
      "id": "prod_Cape-Gourmet_143",
      "productName": "Cape Gourmet Milk",
      "imageUrl": "https://images.unsplash.com/photo-1635436339396-3e04a4a5879a?q=80&w=600",
      "imageHint": "milk gallon jug"
    },
    {
      "id": "prod_Cape-Gourmet_144",
      "productName": "Cape Gourmet Spring Water",
      "imageUrl": "https://images.unsplash.com/photo-1543253724-358c9b42937a?q=80&w=600",
      "imageHint": "water bottle pack"
    },
    {
      "id": "prod_Cape-Gourmet_145",
      "productName": "Cape Gourmet Salad Mix",
      "imageUrl": "https://images.unsplash.com/photo-1550305103-a4e1a062c39d?q=80&w=600",
      "imageHint": "packaged salad bag"
    },
    {
      "id": "prod_Cape-Gourmet_146",
      "productName": "Cape Gourmet Frozen Vegetables",
      "imageUrl": "https://images.unsplash.com/photo-1583025624738-44d039f9765e?q=80&w=600",
      "imageHint": "frozen vegetable bag"
    },
    {
      "id": "prod_Cape-Gourmet_147",
      "productName": "Cape Gourmet Low Fat Ice Cream Sandwiches",
      "imageUrl": "https://images.unsplash.com/photo-1625800938639-c02f52c1e48f?q=80&w=600",
      "imageHint": "ice cream sandwich box"
    },
    {
      "id": "prod_Cape-Gourmet_148",
      "productName": "Cape Gourmet Organic Chipotle Veggie Burgers",
      "imageUrl": "https://images.unsplash.com/photo-1619899383833-911c015957e7?q=80&w=600",
      "imageHint": "veggie burger box"
    },
    {
      "id": "prod_Cape-Gourmet_149",
      "productName": "Cape Gourmet Korean Inspired Cauliflower Bowl",
      "imageUrl": "https://images.unsplash.com/photo-1630384313348-1335b8857504?q=80&w=600",
      "imageHint": "frozen meal bowl"
    },
    {
      "id": "prod_Cape-Gourmet_150",
      "productName": "Cape Gourmet Vegan Plant-Based Meatless Cheesesteak Dumplings",
      "imageUrl": "https://images.unsplash.com/photo-1628864703554-bab4d88258a1?q=80&w=600",
      "imageHint": "frozen dumplings bag"
    },
    {
      "id": "prod_Cape-Gourmet_151",
      "productName": "Cape Gourmet Bath Tissue",
      "imageUrl": "https://images.unsplash.com/photo-1604323832139-3c1a29a39985?q=80&w=600",
      "imageHint": "toilet paper pack"
    },
    {
      "id": "prod_Cape-Gourmet_152",
      "productName": "Cape Gourmet Paper Towels",
      "imageUrl": "https://images.unsplash.com/photo-1609135394994-3a5c4343a496?q=80&w=600",
      "imageHint": "paper towel rolls"
    },
    {
      "id": "prod_Cape-Gourmet_153",
      "productName": "Cape Gourmet Deli Roast Beef",
      "imageUrl": "https://images.unsplash.com/photo-1591054198115-f6a6174a77a9?q=80&w=600",
      "imageHint": "packaged deli meat"
    },
    {
      "id": "prod_Cape-Gourmet_154",
      "productName": "Cape Gourmet Deli Swiss Cheese",
      "imageUrl": "https://images.unsplash.com/photo-1564835415911-35243338bbea?q=80&w=600",
      "imageHint": "packaged sliced cheese"
    },
    {
      "id": "prod_Cape-Gourmet_155",
      "productName": "Cape Gourmet Fresh Chicken Breast",
      "imageUrl": "https://images.unsplash.com/photo-1613564797125-afe133d74868?q=80&w=600",
      "imageHint": "packaged chicken breast"
    },
    {
      "id": "prod_Cape-Gourmet_156",
      "productName": "Cape Gourmet Whole Wheat Bread",
      "imageUrl": "https://images.unsplash.com/photo-1598373182133-52452f741796?q=80&w=600",
      "imageHint": "bread loaf"
    },
    {
      "id": "prod_Cape-Gourmet_157",
      "productName": "Cape Gourmet Organic Eggs",
      "imageUrl": "https://images.unsplash.com/photo-1587573089734-09cb69c0f2b4?q=80&w=600",
      "imageHint": "egg carton"
    },
    {
      "id": "prod_Cape-Gourmet_158",
      "productName": "Cape Gourmet Shredded Cheddar Cheese",
      "imageUrl": "https://images.unsplash.com/photo-1644783344605-3b7a5a542618?q=80&w=600",
      "imageHint": "shredded cheese bag"
    },
    {
      "id": "prod_Cape-Gourmet_159",
      "productName": "Cape Gourmet Tomato Ketchup",
      "imageUrl": "https://images.unsplash.com/photo-1585437895315-7a8f9598fd72?q=80&w=600",
      "imageHint": "ketchup bottle"
    },
    {
      "id": "prod_Cape-Gourmet_160",
      "productName": "Cape Gourmet Olive Oil",
      "imageUrl": "https://images.unsplash.com/photo-1579222384078-622839387258?q=80&w=600",
      "imageHint": "olive oil bottle"
    },
    {
      "id": "prod_Cape-Gourmet_161",
      "productName": "Cape Gourmet Chocolate Bar",
      "imageUrl": "https://images.unsplash.com/photo-1627462249557-4139f4853b06?q=80&w=600",
      "imageHint": "chocolate bar wrapper"
    },
    {
      "id": "prod_Cape-Gourmet_162",
      "productName": "Cape Gourmet Almond Butter",
      "imageUrl": "https://images.unsplash.com/photo-1620921280922-12f9937e956b?q=80&w=600",
      "imageHint": "almond butter jar"
    },
    {
      "id": "prod_Cape-Gourmet_163",
      "productName": "Cape Gourmet Cereal",
      "imageUrl": "https://images.unsplash.com/photo-1585473482704-5d4653634863?q=80&w=600",
      "imageHint": "cereal box"
    },
    {
      "id": "prod_Cape-Gourmet_164",
      "productName": "Cape Gourmet Granola Bars",
      "imageUrl": "https://images.unsplash.com/photo-1554522965-084a33191334?q=80&w=600",
      "imageHint": "granola bar box"
    },
    {
      "id": "prod_Cape-Gourmet_165",
      "productName": "Cape Gourmet Greek Yogurt",
      "imageUrl": "https://images.unsplash.com/photo-1559598467-f8b76c8155d0?q=80&w=600",
      "imageHint": "yogurt container"
    },
    {
      "id": "prod_Cape-Gourmet_166",
      "productName": "Cape Gourmet Coffee Beans",
      "imageUrl": "https://images.unsplash.com/photo-1511537190424-bbbab87ac5eb?q=80&w=600",
      "imageHint": "coffee bean bag"
    },
    {
      "id": "prod_Cape-Gourmet_167",
      "productName": "Cape Gourmet Butter",
      "imageUrl": "https://images.unsplash.com/photo-1622240506294-0a93a8a3d248?q=80&w=600",
      "imageHint": "butter sticks"
    },
    {
      "id": "prod_Cape-Gourmet_168",
      "productName": "Cape Gourmet Frozen Pizza",
      "imageUrl": "https://images.unsplash.com/photo-1565299624946-b28f40a0ae38?q=80&w=600",
      "imageHint": "frozen pizza box"
    }
  ]
}